{
  "schedule": {
    "schedule_id": "3A021JEHN02756_CifarDense_schedule_048",
    "device_id": "3A021JEHN02756",
    "chunks": [
      {
        "name": "chunk1",
        "hardware": "little",
        "threads": 4,
        "stages": [
          1,
          2
        ]
      },
      {
        "name": "chunk2",
        "hardware": "big",
        "threads": 2,
        "stages": [
          3,
          4
        ]
      },
      {
        "name": "chunk3",
        "hardware": "medium",
        "threads": 2,
        "stages": [
          5
        ]
      },
      {
        "name": "chunk4",
        "hardware": "gpu",
        "threads": 1,
        "stages": [
          6,
          7,
          8,
          9
        ]
      }
    ]
  },
  "total_time": 97.58000000000001,
  "max_chunk_time": 36.45
}