{
  "schedule": {
    "schedule_id": "ce0717178d7758b00b7e_CifarDense_schedule_003",
    "device_id": "ce0717178d7758b00b7e",
    "chunks": [
      {
        "name": "chunk1",
        "hardware": "little",
        "threads": 4,
        "stages": [
          1,
          2,
          3
        ],
        "time": 40.616652133098114
      },
      {
        "name": "chunk2",
        "hardware": "gpu",
        "threads": 0,
        "stages": [
          4,
          5,
          6
        ],
        "time": 92.7087606378175
      },
      {
        "name": "chunk3",
        "hardware": "big",
        "threads": 4,
        "stages": [
          7,
          8,
          9
        ],
        "time": 94.10993097586945
      }
    ]
  },
  "max_chunk_time": 94.10993097586945
}